{
  "sections": {
    "hero": {
      "type": "hero",
      "settings": {
        "hero_image": "shopify:\/\/shop_images\/hero.png",
        "title": "Shoulder bag collection",
        "button_text": "Explore now",
        "url": ""
      }
    },
    "second": {
      "type": "collection-grid",
      "settings": {
        "collection": ""
      }
    },
    "collection_grid_QcG8RK": {
      "type": "collection-grid",
      "settings": {
        "collection": "just-landed"
      }
    }
  },
  "order": [
    "hero",
    "second",
    "collection_grid_QcG8RK"
  ]
}
